{
  "version" : 0.0,
  "regression_constraints" : {
    "mae" : {
      "threshold" : 92.61031873933561,
      "comparison_operator" : "GreaterThanThreshold"
    },
    "mse" : {
      "threshold" : 9805.263247773544,
      "comparison_operator" : "GreaterThanThreshold"
    },
    "rmse" : {
      "threshold" : 99.02152921346723,
      "comparison_operator" : "GreaterThanThreshold"
    },
    "r2" : {
      "threshold" : -85.9436657088415,
      "comparison_operator" : "LessThanThreshold"
    }
  }
}