{
  "version" : 0.0,
  "regression_constraints" : {
    "mae" : {
      "threshold" : 39.58523440361023,
      "comparison_operator" : "GreaterThanThreshold"
    },
    "mse" : {
      "threshold" : 2842.260041387725,
      "comparison_operator" : "GreaterThanThreshold"
    },
    "rmse" : {
      "threshold" : 53.312850621475164,
      "comparison_operator" : "GreaterThanThreshold"
    },
    "r2" : {
      "threshold" : 0.9425400555772636,
      "comparison_operator" : "LessThanThreshold"
    }
  }
}